mistune_contrib/__init__.py
mistune_contrib/highlight.py
mistune_contrib/math.py
mistune_contrib/meta.py
mistune_contrib/toc.py
mistune_contrib-0.1.dist-info/DESCRIPTION.rst
mistune_contrib-0.1.dist-info/METADATA
mistune_contrib-0.1.dist-info/metadata.json
mistune_contrib-0.1.dist-info/RECORD
mistune_contrib-0.1.dist-info/top_level.txt
mistune_contrib-0.1.dist-info/WHEEL
