Metadata-Version: 2.0
Name: mistune-contrib
Version: 0.1
Summary: Contribution for Mistune
Home-page: https://github.com/lepture/mistune-contrib
Author: Hsiaoming Yang
Author-email: me@lepture.com
License: BSD
Platform: any
Classifier: Development Status :: 4 - Beta
Classifier: Environment :: Web Environment
Classifier: Intended Audience :: Developers
Classifier: License :: OSI Approved :: BSD License
Classifier: Operating System :: OS Independent
Classifier: Programming Language :: Python
Classifier: Programming Language :: Python :: 2.6
Classifier: Programming Language :: Python :: 2.7
Classifier: Programming Language :: Python :: 3.3
Classifier: Programming Language :: Python :: 3.4
Classifier: Programming Language :: Python :: Implementation :: CPython
Classifier: Programming Language :: Python :: Implementation :: PyPy
Classifier: Topic :: Text Processing :: Markup
Classifier: Topic :: Software Development :: Libraries :: Python Modules
